pyoak/__init__.py
pyoak/codegen.py
pyoak/config.py
pyoak/error.py
pyoak/file.py
pyoak/legacy/__init__.py
pyoak/legacy/error.py
pyoak/legacy/helpers.py
pyoak/legacy/match/__init__.py
pyoak/legacy/match/error.py
pyoak/legacy/match/grammar.py
pyoak/legacy/match/helpers.py
pyoak/legacy/match/pattern.py
pyoak/legacy/match/xpath.py
pyoak/legacy/node.py
pyoak/match/__init__.py
pyoak/match/error.py
pyoak/match/grammar.py
pyoak/match/helpers.py
pyoak/match/pattern.py
pyoak/match/xpath.py
pyoak/node.py
pyoak/origin.py
pyoak/py.typed
pyoak/serialize.py
pyoak/tree.py
pyoak/typing.py
pyoak/visitor.py
pyoak-2.1.0.dist-info/LICENSE
pyoak-2.1.0.dist-info/METADATA
pyoak-2.1.0.dist-info/WHEEL
pyoak-2.1.0.dist-info/RECORD
