Metadata-Version: 2.1
Name: pyoak
Version: 2.1.0
Summary: Library for building and working with arbitrary ASTs on top dataclasses
Home-page: https://github.com/mishamsk/pyoak
License: MIT
Author: Mike Perlov
Author-email: mishamsk@gmail.com
Requires-Python: >=3.10
Classifier: Development Status :: 5 - Production/Stable
Classifier: Intended Audience :: Developers
Classifier: License :: OSI Approved :: MIT License
Classifier: Natural Language :: English
Classifier: Programming Language :: Python :: 3
Classifier: Programming Language :: Python :: 3.10
Classifier: Programming Language :: Python :: 3.11
Requires-Dist: chardet (>=5.0.0,<6.0.0)
Requires-Dist: lark (>=1.1.5,<2.0.0)
Requires-Dist: mashumaro (>=3.8.1)
Requires-Dist: msgpack (>=1.0.4,<2.0.0)
Requires-Dist: orjson (>=3.8.7,<4.0.0)
Requires-Dist: pyyaml (>=6.0.0,<7.0.0)
Requires-Dist: rich (>=12.5.0,<14)
